<?xml version="1.0" encoding="UTF-8"?><group xmlns="urn:oma:xml:poc:list-service" xmlns:rl="urn:ietf:params:xml:ns:resource-lists" xmlns:mcpttgi="urn:3gpp:ns:mcpttGroupInfo:1.0" xmlns:ocp="urn:oma:xml:xdm:common-policy" xmlns:cp="urn:ietf:params:xml:ns:common-policy" xmlns:oxe="urn:oma:xml:xdm:extensions">    <list-service etag="gkwWJaNIYpQ" uri="tel:+82999990842" public="true">        <display-name xml:lang="en-kr">단말시험_미디어ON</display-name>        <list>            <entry uri="tel:+821352995409">                <rl:display-name xml:lang="en-kr">서울운영센터 수행사 T QAT검증20</rl:display-name>                <mcpttgi:user-priority>1</mcpttgi:user-priority>                <mcpttgi:participant-type>General_UE</mcpttgi:participant-type>            </entry>            <entry uri="tel:+821352030555">                <rl:display-name xml:lang="en-kr">821352030555</rl:display-name>                <mcpttgi:user-priority>3</mcpttgi:user-priority>                <mcpttgi:participant-type>General_UE</mcpttgi:participant-type>            </entry>            <entry uri="tel:+821352030557">                <rl:display-name xml:lang="en-kr">821352030557</rl:display-name>                <mcpttgi:user-priority>3</mcpttgi:user-priority>                <mcpttgi:participant-type>General_UE</mcpttgi:participant-type>            </entry>            <entry uri="tel:+821352030558">                <rl:display-name xml:lang="en-kr">821352030558</rl:display-name>                <mcpttgi:user-priority>3</mcpttgi:user-priority>                <mcpttgi:participant-type>General_UE</mcpttgi:participant-type>            </entry>            <entry uri="tel:+821352995407">                <rl:display-name xml:lang="en-kr">서울운영센터 수행사 T QAT검증18</rl:display-name>                <mcpttgi:user-priority>1</mcpttgi:user-priority>                <mcpttgi:participant-type>General_UE</mcpttgi:participant-type>            </entry>            <entry uri="tel:+821352030501">                <rl:display-name xml:lang="en-kr">/서울관악/경비/50510</rl:display-name>                <mcpttgi:user-priority>3</mcpttgi:user-priority>                <mcpttgi:participant-type>General_UE</mcpttgi:participant-type>            </entry>            <entry uri="tel:+821352995400">                <rl:display-name xml:lang="en-kr">서울운영센터 수행사 T QAT검증11</rl:display-name>                <mcpttgi:user-priority>1</mcpttgi:user-priority>                <mcpttgi:participant-type>General_UE</mcpttgi:participant-type>            </entry>            <entry uri="tel:+821352030436">                <rl:display-name xml:lang="en-kr">821352030436</rl:display-name>                <mcpttgi:user-priority>1</mcpttgi:user-priority>                <mcpttgi:participant-type>General_UE</mcpttgi:participant-type>            </entry>            <entry uri="tel:+821352030114">                <rl:display-name xml:lang="en-kr">821352030114_D</rl:display-name>                <mcpttgi:user-priority>2</mcpttgi:user-priority>                <mcpttgi:participant-type>General_UE</mcpttgi:participant-type>            </entry>            <entry uri="tel:+821352001410">                <rl:display-name xml:lang="en-kr">821352001410_B</rl:display-name>                <mcpttgi:user-priority>3</mcpttgi:user-priority>                <mcpttgi:participant-type>General_UE</mcpttgi:participant-type>            </entry>            <entry uri="tel:+821352030115">                <rl:display-name xml:lang="en-kr">821352030115</rl:display-name>                <mcpttgi:user-priority>2</mcpttgi:user-priority>                <mcpttgi:participant-type>General_UE</mcpttgi:participant-type>            </entry>            <entry uri="tel:+821352030438">                <rl:display-name xml:lang="en-kr">821352030438</rl:display-name>                <mcpttgi:user-priority>1</mcpttgi:user-priority>                <mcpttgi:participant-type>General_UE</mcpttgi:participant-type>            </entry>            <entry uri="tel:+821352030437">                <rl:display-name xml:lang="en-kr">821352030437</rl:display-name>                <mcpttgi:user-priority>1</mcpttgi:user-priority>                <mcpttgi:participant-type>General_UE</mcpttgi:participant-type>            </entry>            <entry uri="tel:+821352995408">                <rl:display-name xml:lang="en-kr">서울운영센터 수행사 T QAT검증19</rl:display-name>                <mcpttgi:user-priority>1</mcpttgi:user-priority>                <mcpttgi:participant-type>General_UE</mcpttgi:participant-type>            </entry>            <entry uri="tel:+821352995403">                <rl:display-name xml:lang="en-kr">서울운영센터 수행사 T QAT검증14</rl:display-name>                <mcpttgi:user-priority>1</mcpttgi:user-priority>                <mcpttgi:participant-type>General_UE</mcpttgi:participant-type>            </entry>            <entry uri="tel:+821352995402">                <rl:display-name xml:lang="en-kr">서울운영센터 수행사 T QAT검증13</rl:display-name>                <mcpttgi:user-priority>1</mcpttgi:user-priority>                <mcpttgi:participant-type>General_UE</mcpttgi:participant-type>            </entry>            <entry uri="tel:+821352001413">                <rl:display-name xml:lang="en-kr">821352001413</rl:display-name>                <mcpttgi:user-priority>1</mcpttgi:user-priority>                <mcpttgi:participant-type>General_UE</mcpttgi:participant-type>            </entry>            <entry uri="tel:+821352030116">                <rl:display-name>821352030116_E</rl:display-name>                <mcpttgi:user-priority>6</mcpttgi:user-priority>                <mcpttgi:participant-type>General_UE</mcpttgi:participant-type>            </entry>            <entry uri="tel:+821352030502">                <rl:display-name>821352030502_F</rl:display-name>                <mcpttgi:user-priority>3</mcpttgi:user-priority>                <mcpttgi:participant-type>General_UE</mcpttgi:participant-type>            </entry>            <entry uri="tel:+821352001409">                <rl:display-name>821352001409_A</rl:display-name>                <mcpttgi:user-priority>1</mcpttgi:user-priority>                <mcpttgi:participant-type>General_UE</mcpttgi:participant-type>            </entry>            <entry uri="tel:+821352995647">                <rl:display-name>서울운영센터 수행사 AM 단말개발8</rl:display-name>                <mcpttgi:user-priority>1</mcpttgi:user-priority>                <mcpttgi:participant-type>General_UE</mcpttgi:participant-type>            </entry>            <entry uri="tel:+821352001414">                <rl:display-name>821352001414</rl:display-name>                <mcpttgi:user-priority>3</mcpttgi:user-priority>                <mcpttgi:participant-type>General_UE</mcpttgi:participant-type>            </entry>            <entry uri="tel:+821352995814">                <rl:display-name>LM75_03</rl:display-name>                <mcpttgi:user-priority>1</mcpttgi:user-priority>                <mcpttgi:participant-type>General_UE</mcpttgi:participant-type>            </entry>        </list>        <mcpttgi:on-network-invite-members>true</mcpttgi:on-network-invite-members>        <mcpttgi:on-network-max-participant-count>10000</mcpttgi:on-network-max-participant-count>        <cp:ruleset>            <cp:rule id="a7c">                <cp:actions>                    <mcpttgi:allow-MCPTT-emergency-call>false</mcpttgi:allow-MCPTT-emergency-call>                </cp:actions>            </cp:rule>        </cp:ruleset>        <mcpttgi:on-network-group-priority>2</mcpttgi:on-network-group-priority>        <mcpttgi:owner>중앙정부</mcpttgi:owner>        <mcpttgi:on-network-hang-timer>PT7200S</mcpttgi:on-network-hang-timer>        <mcpttgi:on-network-maximum-duration>PT86400S</mcpttgi:on-network-maximum-duration>        <mcpttgi:protect-media>true</mcpttgi:protect-media>    </list-service></group>